[{"contributors": null, "truncated": false, "text": "Our thoughts and prayers go to everyone affected by the attack in Paris. #PrayforParis \ud83d\ude4f https://t.co/bOURH3uB46", "is_quote_status": false, "in_reply_to_status_id": null, "id": {"numberLong": "665386099502485505"}, "favorite_count": 0, "source": "<a href=\"http://twitter.com/download/android\" rel=\"nofollow\">Twitter for Android</a>", "retweeted": false, "coordinates": null, "timestamp_ms": "1447475383054", "entities": {"symbols": [], "media": [{"expanded_url": "http://twitter.com/bangtanitl/status/665386099502485505/photo/1", "display_url": "pic.twitter.com/bOURH3uB46", "url": "https://t.co/bOURH3uB46", "media_url_https": "https://pbs.twimg.com/media/CTvtILKUkAAB1al.jpg", "id_str": "665386094658097152", "sizes": {"large": {"h": 627, "w": 638, "resize": "fit"}, "small": {"h": 334, "w": 340, "resize": "fit"}, "medium": {"h": 589, "w": 600, "resize": "fit"}, "thumb": {"h": 150, "w": 150, "resize": "crop"}}, "indices": [89, 112], "type": "photo", "id": {"numberLong": "665386094658097152"}, "media_url": "http://pbs.twimg.com/media/CTvtILKUkAAB1al.jpg"}], "hashtags": [{"indices": [73, 86], "text": "PrayforParis"}], "user_mentions": [], "urls": []}, "in_reply_to_screen_name": null, "id_str": "665386099502485505", "retweet_count": 0, "in_reply_to_user_id": null, "favorited": false, "user": {"follow_request_sent": null, "profile_use_background_image": true, "geo_enabled": false, "description": "ARMY Base is an international fanbase for the Korean boy group Bangtan Boys. | Start: 150101~ing | Please credit us. | @BTS_ABS", "verified": false, "profile_image_url_https": "https://pbs.twimg.com/profile_images/588783508723736577/P7Gm_whF_normal.jpg", "profile_sidebar_fill_color": "000000", "id": {"numberLong": "2934423981"}, "profile_text_color": "000000", "followers_count": 44907, "protected": false, "location": null, "default_profile_image": false, "id_str": "2934423981", "utc_offset": 3600, "statuses_count": 9920, "profile_background_color": "FFF04D", "friends_count": 433, "profile_link_color": "0099CC", "profile_image_url": "http://pbs.twimg.com/profile_images/588783508723736577/P7Gm_whF_normal.jpg", "notifications": null, "profile_background_image_url_https": "https://pbs.twimg.com/profile_background_images/589811211601973248/hwmY3QBR.jpg", "profile_banner_url": "https://pbs.twimg.com/profile_banners/2934423981/1429542865", "profile_background_image_url": "http://pbs.twimg.com/profile_background_images/589811211601973248/hwmY3QBR.jpg", "screen_name": "bangtanitl", "lang": "en", "following": null, "profile_background_tile": false, "favourites_count": 29, "name": "ARMY Base", "url": "https://bangtanintl.wordpress.com/", "created_at": "Sun Dec 21 00:24:24 +0000 2014", "contributors_enabled": false, "time_zone": "Warsaw", "profile_sidebar_border_color": "000000", "default_profile": false, "is_translator": false, "listed_count": 214}, "geo": null, "in_reply_to_user_id_str": null, "possibly_sensitive": false, "lang": "en", "created_at": "Sat Nov 14 04:29:43 +0000 2015", "filter_level": "low", "in_reply_to_status_id_str": null, "place": null, "extended_entities": {"media": [{"expanded_url": "http://twitter.com/bangtanitl/status/665386099502485505/photo/1", "display_url": "pic.twitter.com/bOURH3uB46", "url": "https://t.co/bOURH3uB46", "media_url_https": "https://pbs.twimg.com/media/CTvtILKUkAAB1al.jpg", "id_str": "665386094658097152", "sizes": {"large": {"h": 627, "w": 638, "resize": "fit"}, "small": {"h": 334, "w": 340, "resize": "fit"}, "medium": {"h": 589, "w": 600, "resize": "fit"}, "thumb": {"h": 150, "w": 150, "resize": "crop"}}, "indices": [89, 112], "type": "photo", "id": {"numberLong": "665386094658097152"}, "media_url": "http://pbs.twimg.com/media/CTvtILKUkAAB1al.jpg"}]}, "_id": {"oid": "5646b8b7bf49a103acde33e0"}},{"contributors":
 null, "truncated": false, "text": "RT @ohlordhes: \"Its an attack not just in the people of France, but this is an attack on all humanity\" -Pres. Obama\n\n#PrayForParis", "is_quote_status": false, "in_reply_to_status_id": null, "id": {"numberLong": "665387806743764992"}, "favorite_count": 0, "source": "<a href=\"http://twitter.com/download/android\" rel=\"nofollow\">Twitter for Android</a>", "retweeted": false, "coordinates": null, "timestamp_ms": "1447475790092", "entities": {"symbols": [], "user_mentions": [{"indices": [3, 13], "screen_name": "ohlordhes", "id": 427748930, "name": "lea", "id_str": "427748930"}], "hashtags": [{"indices": [117, 130], "text": "PrayForParis"}], "urls": []}, "in_reply_to_screen_name": null, "id_str": "665387806743764992", "retweet_count": 0, "in_reply_to_user_id": null, "favorited": false, "retweeted_status": {"contributors": null, "truncated": false, "text": "\"Its an attack not just in the people of France, but this is an attack on all humanity\" -Pres. Obama\n\n#PrayForParis", "is_quote_status": false, "in_reply_to_status_id": null, "id": {"numberLong": "665367106238607360"}, "favorite_count": 77, "entities": {"symbols": [], "user_mentions": [], "hashtags": [{"indices": [102, 115], "text": "PrayForParis"}], "urls": []}, "retweeted": false, "coordinates": null, "source": "<a href=\"http://twitter.com/download/iphone\" rel=\"nofollow\">Twitter for iPhone</a>", "in_reply_to_screen_name": null, "id_str": "665367106238607360", "retweet_count": 66, "in_reply_to_user_id": null, "favorited": false, "user": {"follow_request_sent": null, "profile_use_background_image": true, "geo_enabled": true, "description": "Rendezvous", "verified": false, "profile_image_url_https": "https://pbs.twimg.com/profile_images/665039235385176064/1tm1oBlz_normal.png", "profile_sidebar_fill_color": "DDEEF6", "id": 427748930, "profile_text_color": "333333", "followers_count": 12240, "protected": false, "location": "IG: zalea.a", "default_profile_image": false, "id_str": "427748930", "utc_offset": -32400, "statuses_count": 60669, "profile_background_color": "C0DEED", "friends_count": 1020, "profile_link_color": "0084B4", "profile_image_url": "http://pbs.twimg.com/profile_images/665039235385176064/1tm1oBlz_normal.png", "notifications": null, "profile_background_image_url_https": "https://abs.twimg.com/images/themes/theme1/bg.png", "profile_banner_url": "https://pbs.twimg.com/profile_banners/427748930/1447410011", "profile_background_image_url": "http://abs.twimg.com/images/themes/theme1/bg.png", "screen_name": "ohlordhes", "lang": "en", "following": null, "profile_background_tile": false, "favourites_count": 14704, "name": "lea", "url": null, "created_at": "Sat Dec 03 22:47:49 +0000 2011", "contributors_enabled": false, "time_zone": "Alaska", "profile_sidebar_border_color": "C0DEED", "default_profile": true, "is_translator": false, "listed_count": 65}, "geo": null, "in_reply_to_user_id_str": null, "lang": "en", "created_at": "Sat Nov 14 03:14:14 +0000 2015", "filter_level": "low", "in_reply_to_status_id_str": null, "place": null}, "user": {"follow_request_sent": null, "profile_use_background_image": true, "geo_enabled": true, "description": "\u271613.02.15 I saw Ed \u2716\n1d | the vamps | 5sos | sel | jus | miley | demi | ed | tom | dylan | harry potter | teen wolf", "verified": false, "profile_image_url_https": "https://pbs.twimg.com/profile_images/665382645178703872/4GOcMdKA_normal.jpg", "profile_sidebar_fill_color": "000000", "id": {"numberLong": "2411030538"}, "profile_text_color": "000000", "followers_count": 1751, "protected": false, "location": "Hogwart", "default_profile_image": false, "id_str": "2411030538", "utc_offset": 3600, "statuses_count": 21591, "profile_background_color": "FFFFFF", "friends_count": 2282, "profile_link_color": "000000", "profile_image_url": "http://pbs.twimg.com/profile_images/665382645178703872/4GOcMdKA_normal.jpg", "notifications": null, "profile_background_image_url_https": "https://pbs.twimg.com/profile_background_images/649232820573831168/8edtzZzY.png", "profile_banner_url": "https://pbs.twimg.com/profile_banners/2411030538/1447465019", "profile_background_image_url": "http://pbs.twimg.com/profile_background_images/649232820573831168/8edtzZzY.png", "screen_name": "__CanWeDance__", "lang": "pl", "following": null, "profile_background_tile": true, "favourites_count": 6765, "name": "p r a y", "url": null, "created_at": "Tue Mar 25 13:43:26 +0000 2014", "contributors_enabled": false, "time_zone": "Warsaw", "profile_sidebar_border_color": "FFFFFF", "default_profile": false, "is_translator": false, "listed_count": 4}, "geo": null, "in_reply_to_user_id_str": null, "lang": "en", "created_at": "Sat Nov 14 04:36:30 +0000 2015", "filter_level": "low", "in_reply_to_status_id_str": null, "place": null, "_id": {"oid": "5646ba4ebf49a103f59709ed"}},{"contributors":
 null, "truncated": false, "text": "RT @Married2TheNite: My brother-in-law drew this sketch after the tragedy today. #PrayForParis \ud83c\uddeb\ud83c\uddf7 @NYDailyNews https://t.co/uumDfq0OWJ", "is_quote_status": false, "in_reply_to_status_id": null, "id": {"numberLong": "665389030733914112"}, "favorite_count": 0, "source": "<a href=\"http://twitter.com/download/android\" rel=\"nofollow\">Twitter for Android</a>", "retweeted": false, "coordinates": null, "timestamp_ms": "1447476081914", "entities": {"symbols": [], "media": [{"source_user_id": 289561555, "source_status_id_str": "665378349213089792", "expanded_url": "http://twitter.com/Married2TheNite/status/665378349213089792/photo/1", "display_url": "pic.twitter.com/uumDfq0OWJ", "source_status_id": {"numberLong": "665378349213089792"}, "media_url_https": "https://pbs.twimg.com/media/CTvmE42WwAAPU2n.jpg", "source_user_id_str": "289561555", "url": "https://t.co/uumDfq0OWJ", "id_str": "665378341621514240", "sizes": {"large": {"h": 640, "w": 640, "resize": "fit"}, "small": {"h": 340, "w": 340, "resize": "fit"}, "medium": {"h": 600, "w": 600, "resize": "fit"}, "thumb": {"h": 150, "w": 150, "resize": "crop"}}, "indices": [111, 134], "type": "photo", "id": {"numberLong": "665378341621514240"}, "media_url": "http://pbs.twimg.com/media/CTvmE42WwAAPU2n.jpg"}], "hashtags": [{"indices": [81, 94], "text": "PrayForParis"}], "user_mentions": [{"indices": [3, 19], "screen_name": "Married2TheNite", "id": 289561555, "name": "Joseph", "id_str": "289561555"}, {"indices": [98, 110], "screen_name": "NYDailyNews", "id": 9763482, "name": "New York Daily News", "id_str": "9763482"}], "urls": []}, "in_reply_to_screen_name": null, "id_str": "665389030733914112", "retweet_count": 0, "in_reply_to_user_id": null, "favorited": false, "retweeted_status": {"contributors": null, "truncated": false, "text": "My brother-in-law drew this sketch after the tragedy today. #PrayForParis \ud83c\uddeb\ud83c\uddf7 @NYDailyNews https://t.co/uumDfq0OWJ", "is_quote_status": false, "in_reply_to_status_id": null, "id": {"numberLong": "665378349213089792"}, "favorite_count": 439, "source": "<a href=\"http://twitter.com/download/iphone\" rel=\"nofollow\">Twitter for iPhone</a>", "retweeted": false, "coordinates": null, "entities": {"symbols": [], "media": [{"expanded_url": "http://twitter.com/Married2TheNite/status/665378349213089792/photo/1", "display_url": "pic.twitter.com/uumDfq0OWJ", "url": "https://t.co/uumDfq0OWJ", "media_url_https": "https://pbs.twimg.com/media/CTvmE42WwAAPU2n.jpg", "id_str": "665378341621514240", "sizes": {"large": {"h": 640, "w": 640, "resize": "fit"}, "small": {"h": 340, "w": 340, "resize": "fit"}, "medium": {"h": 600, "w": 600, "resize": "fit"}, "thumb": {"h": 150, "w": 150, "resize": "crop"}}, "indices": [90, 113], "type": "photo", "id": {"numberLong": "665378341621514240"}, "media_url": "http://pbs.twimg.com/media/CTvmE42WwAAPU2n.jpg"}], "hashtags": [{"indices": [60, 73], "text": "PrayForParis"}], "user_mentions": [{"indices": [77, 89], "screen_name": "NYDailyNews", "id": 9763482, "name": "New York Daily News", "id_str": "9763482"}], "urls": []}, "in_reply_to_screen_name": null, "id_str": "665378349213089792", "retweet_count": 346, "in_reply_to_user_id": null, "favorited": false, "user": {"follow_request_sent": null, "profile_use_background_image": true, "geo_enabled": true, "description": "take me back to the basics and the simple life", "verified": false, "profile_image_url_https": "https://pbs.twimg.com/profile_images/653816086048194561/gls-cUbu_normal.jpg", "profile_sidebar_fill_color": "EFEFEF", "id": 289561555, "profile_text_color": "333333", "followers_count": 1399, "protected": false, "location": "New Jersey", "default_profile_image": false, "id_str": "289561555", "utc_offset": -18000, "statuses_count": 11523, "profile_background_color": "000000", "friends_count": 1600, "profile_link_color": "0541A8", "profile_image_url": "http://pbs.twimg.com/profile_images/653816086048194561/gls-cUbu_normal.jpg", "notifications": null, "profile_background_image_url_https": "https://pbs.twimg.com/profile_background_images/518122727551422464/Kh-sAMNZ.jpeg", "profile_banner_url": "https://pbs.twimg.com/profile_banners/289561555/1444717156", "profile_background_image_url": "http://pbs.twimg.com/profile_background_images/518122727551422464/Kh-sAMNZ.jpeg", "screen_name": "Married2TheNite", "lang": "en", "following": null, "profile_background_tile": true, "favourites_count": 6571, "name": "Joseph", "url": "http://about.me/Married2TheNite", "created_at": "Thu Apr 28 21:28:00 +0000 2011", "contributors_enabled": false, "time_zone": "Eastern Time (US & Canada)", "profile_sidebar_border_color": "000000", "default_profile": false, "is_translator": false, "listed_count": 9}, "geo": null, "in_reply_to_user_id_str": null, "possibly_sensitive": false, "lang": "en", "created_at": "Sat Nov 14 03:58:55 +0000 2015", "filter_level": "low", "in_reply_to_status_id_str": null, "place": null, "extended_entities": {"media": [{"expanded_url": "http://twitter.com/Married2TheNite/status/665378349213089792/photo/1", "display_url": "pic.twitter.com/uumDfq0OWJ", "url": "https://t.co/uumDfq0OWJ", "media_url_https": "https://pbs.twimg.com/media/CTvmE42WwAAPU2n.jpg", "id_str": "665378341621514240", "sizes": {"large": {"h": 640, "w": 640, "resize": "fit"}, "small": {"h": 340, "w": 340, "resize": "fit"}, "medium": {"h": 600, "w": 600, "resize": "fit"}, "thumb": {"h": 150, "w": 150, "resize": "crop"}}, "indices": [90, 113], "type": "photo", "id": {"numberLong": "665378341621514240"}, "media_url": "http://pbs.twimg.com/media/CTvmE42WwAAPU2n.jpg"}]}}, "user": {"follow_request_sent": null, "profile_use_background_image": true, "geo_enabled": true, "description": "pami\u0119taj dziecko, nigdy nie przywi\u0105zuj si\u0119 zbyt emocjonalnie do zespo\u0142u, bo to ci\u0119 zniszczy.", "verified": false, "profile_image_url_https": "https://pbs.twimg.com/profile_images/662629312428949505/hISXeHFM_normal.jpg", "profile_sidebar_fill_color": "EFEFEF", "id": 1126281842, "profile_text_color": "333333", "followers_count": 4373, "protected": false, "location": "5sos tay ari ed gd mcr hp tw \u2741", "default_profile_image": false, "id_str": "1126281842", "utc_offset": 3600, "statuses_count": 95862, "profile_background_color": "000000", "friends_count": 2852, "profile_link_color": "111111", "profile_image_url": "http://pbs.twimg.com/profile_images/662629312428949505/hISXeHFM_normal.jpg", "notifications": null, "profile_background_image_url_https": "https://pbs.twimg.com/profile_background_images/632837945200762880/CF64uxFJ.jpg", "profile_banner_url": "https://pbs.twimg.com/profile_banners/1126281842/1446834352", "profile_background_image_url": "http://pbs.twimg.com/profile_background_images/632837945200762880/CF64uxFJ.jpg", "screen_name": "fooxnir", "lang": "en", "following": null, "profile_background_tile": true, "favourites_count": 2055, "name": "oponk\u00e3 *\u2727\uff9f", "url": null, "created_at": "Sun Jan 27 21:37:51 +0000 2013", "contributors_enabled": false, "time_zone": "Warsaw", "profile_sidebar_border_color": "000000", "default_profile": false, "is_translator": false, "listed_count": 5}, "geo": null, "in_reply_to_user_id_str": null, "possibly_sensitive": false, "lang": "en", "created_at": "Sat Nov 14 04:41:21 +0000 2015", "filter_level": "low", "in_reply_to_status_id_str": null, "place": null, "extended_entities": {"media": [{"source_user_id": 289561555, "source_status_id_str": "665378349213089792", "expanded_url": "http://twitter.com/Married2TheNite/status/665378349213089792/photo/1", "display_url": "pic.twitter.com/uumDfq0OWJ", "source_status_id": {"numberLong": "665378349213089792"}, "media_url_https": "https://pbs.twimg.com/media/CTvmE42WwAAPU2n.jpg", "source_user_id_str": "289561555", "url": "https://t.co/uumDfq0OWJ", "id_str": "665378341621514240", "sizes": {"large": {"h": 640, "w": 640, "resize": "fit"}, "small": {"h": 340, "w": 340, "resize": "fit"}, "medium": {"h": 600, "w": 600, "resize": "fit"}, "thumb": {"h": 150, "w": 150, "resize": "crop"}}, "indices": [111, 134], "type": "photo", "id": {"numberLong": "665378341621514240"}, "media_url": "http://pbs.twimg.com/media/CTvmE42WwAAPU2n.jpg"}]}, "_id": {"oid": "5646bb72bf49a10439b0808d"}},{"contributors":
 null, "truncated": false, "text": "RT @highbythehills: \"when the city of light goes dark, the rest of the world lights up for them\" #PrayForParis https://t.co/8htAdoLic9", "is_quote_status": false, "in_reply_to_status_id": null, "id": {"numberLong": "665389447609978880"}, "favorite_count": 0, "source": "<a href=\"http://twitter.com/download/android\" rel=\"nofollow\">Twitter for Android</a>", "retweeted": false, "coordinates": null, "timestamp_ms": "1447476181305", "entities": {"symbols": [], "media": [{"source_user_id": 380473861, "source_status_id_str": "665388460929323008", "expanded_url": "http://twitter.com/highbythehills/status/665388460929323008/photo/1", "display_url": "pic.twitter.com/8htAdoLic9", "source_status_id": {"numberLong": "665388460929323008"}, "media_url_https": "https://pbs.twimg.com/media/CTvvRRSWEAApAlz.jpg", "source_user_id_str": "380473861", "url": "https://t.co/8htAdoLic9", "id_str": "665388449944440832", "sizes": {"large": {"h": 419, "w": 417, "resize": "fit"}, "small": {"h": 341, "w": 340, "resize": "fit"}, "medium": {"h": 419, "w": 417, "resize": "fit"}, "thumb": {"h": 150, "w": 150, "resize": "crop"}}, "indices": [111, 134], "type": "photo", "id": {"numberLong": "665388449944440832"}, "media_url": "http://pbs.twimg.com/media/CTvvRRSWEAApAlz.jpg"}], "hashtags": [{"indices": [97, 110], "text": "PrayForParis"}], "user_mentions": [{"indices": [3, 18], "screen_name": "highbythehills", "id": 380473861, "name": "mf.", "id_str": "380473861"}], "urls": []}, "in_reply_to_screen_name": null, "id_str": "665389447609978880", "retweet_count": 0, "in_reply_to_user_id": null, "favorited": false, "retweeted_status": {"contributors": null, "truncated": false, "text": "\"when the city of light goes dark, the rest of the world lights up for them\" #PrayForParis https://t.co/8htAdoLic9", "is_quote_status": false, "in_reply_to_status_id": null, "id": {"numberLong": "665388460929323008"}, "favorite_count": 36, "source": "<a href=\"http://twitter.com/download/iphone\" rel=\"nofollow\">Twitter for iPhone</a>", "retweeted": false, "coordinates": null, "entities": {"symbols": [], "media": [{"expanded_url": "http://twitter.com/highbythehills/status/665388460929323008/photo/1", "display_url": "pic.twitter.com/8htAdoLic9", "url": "https://t.co/8htAdoLic9", "media_url_https": "https://pbs.twimg.com/media/CTvvRRSWEAApAlz.jpg", "id_str": "665388449944440832", "sizes": {"large": {"h": 419, "w": 417, "resize": "fit"}, "small": {"h": 341, "w": 340, "resize": "fit"}, "medium": {"h": 419, "w": 417, "resize": "fit"}, "thumb": {"h": 150, "w": 150, "resize": "crop"}}, "indices": [91, 114], "type": "photo", "id": {"numberLong": "665388449944440832"}, "media_url": "http://pbs.twimg.com/media/CTvvRRSWEAApAlz.jpg"}], "hashtags": [{"indices": [77, 90], "text": "PrayForParis"}], "user_mentions": [], "urls": []}, "in_reply_to_screen_name": null, "id_str": "665388460929323008", "retweet_count": 60, "in_reply_to_user_id": null, "favorited": false, "user": {"follow_request_sent": null, "profile_use_background_image": true, "geo_enabled": true, "description": "Through the wire i'm watching you like this, imagining you're mine.", "verified": false, "profile_image_url_https": "https://pbs.twimg.com/profile_images/664912101618671616/edYB9IM5_normal.jpg", "profile_sidebar_fill_color": "EEEBF0", "id": 380473861, "profile_text_color": "452840", "followers_count": 4456, "protected": false, "location": "25.04.14 || 19.04.15 // SSDR\u2661", "default_profile_image": false, "id_str": "380473861", "utc_offset": -21600, "statuses_count": 157620, "profile_background_color": "FFFFFF", "friends_count": 3001, "profile_link_color": "000000", "profile_image_url": "http://pbs.twimg.com/profile_images/664912101618671616/edYB9IM5_normal.jpg", "notifications": null, "profile_background_image_url_https": "https://pbs.twimg.com/profile_background_images/443376086852698112/fRAHMcv_.jpeg", "profile_banner_url": "https://pbs.twimg.com/profile_banners/380473861/1447159157", "profile_background_image_url": "http://pbs.twimg.com/profile_background_images/443376086852698112/fRAHMcv_.jpeg", "screen_name": "highbythehills", "lang": "en", "following": null, "profile_background_tile": true, "favourites_count": 1081, "name": "mf.", "url": "https://twitter.com/zaynmalik/status/190276041212833794", "created_at": "Mon Sep 26 18:18:00 +0000 2011", "contributors_enabled": false, "time_zone": "Central Time (US & Canada)", "profile_sidebar_border_color": "FFFFFF", "default_profile": false, "is_translator": false, "listed_count": 27}, "geo": null, "in_reply_to_user_id_str": null, "possibly_sensitive": false, "lang": "en", "created_at": "Sat Nov 14 04:39:06 +0000 2015", "filter_level": "low", "in_reply_to_status_id_str": null, "place": null, "extended_entities": {"media": [{"expanded_url": "http://twitter.com/highbythehills/status/665388460929323008/photo/1", "display_url": "pic.twitter.com/8htAdoLic9", "url": "https://t.co/8htAdoLic9", "media_url_https": "https://pbs.twimg.com/media/CTvvRRSWEAApAlz.jpg", "id_str": "665388449944440832", "sizes": {"large": {"h": 419, "w": 417, "resize": "fit"}, "small": {"h": 341, "w": 340, "resize": "fit"}, "medium": {"h": 419, "w": 417, "resize": "fit"}, "thumb": {"h": 150, "w": 150, "resize": "crop"}}, "indices": [91, 114], "type": "photo", "id": {"numberLong": "665388449944440832"}, "media_url": "http://pbs.twimg.com/media/CTvvRRSWEAApAlz.jpg"}]}}, "user": {"follow_request_sent": null, "profile_use_background_image": true, "geo_enabled": true, "description": "jb", "verified": false, "profile_image_url_https": "https://pbs.twimg.com/profile_images/665239062761054208/Ps4G4ajd_normal.jpg", "profile_sidebar_fill_color": "DDEEF6", "id": 588279293, "profile_text_color": "333333", "followers_count": 6089, "protected": false, "location": null, "default_profile_image": false, "id_str": "588279293", "utc_offset": 3600, "statuses_count": 22088, "profile_background_color": "ABB8C2", "friends_count": 6297, "profile_link_color": "3B94D9", "profile_image_url": "http://pbs.twimg.com/profile_images/665239062761054208/Ps4G4ajd_normal.jpg", "notifications": null, "profile_background_image_url_https": "https://pbs.twimg.com/profile_background_images/551691602838564865/b_Eki_7y.png", "profile_banner_url": "https://pbs.twimg.com/profile_banners/588279293/1447440424", "profile_background_image_url": "http://pbs.twimg.com/profile_background_images/551691602838564865/b_Eki_7y.png", "screen_name": "LovMyKidrauhlx", "lang": "pl", "following": null, "profile_background_tile": true, "favourites_count": 3186, "name": "\u2728purpose\u2728", "url": null, "created_at": "Wed May 23 13:16:40 +0000 2012", "contributors_enabled": false, "time_zone": "Warsaw", "profile_sidebar_border_color": "FFFFFF", "default_profile": false, "is_translator": false, "listed_count": 6}, "geo": null, "in_reply_to_user_id_str": null, "possibly_sensitive": false, "lang": "en", "created_at": "Sat Nov 14 04:43:01 +0000 2015", "filter_level": "low", "in_reply_to_status_id_str": null, "place": null, "extended_entities": {"media": [{"source_user_id": 380473861, "source_status_id_str": "665388460929323008", "expanded_url": "http://twitter.com/highbythehills/status/665388460929323008/photo/1", "display_url": "pic.twitter.com/8htAdoLic9", "source_status_id": {"numberLong": "665388460929323008"}, "media_url_https": "https://pbs.twimg.com/media/CTvvRRSWEAApAlz.jpg", "source_user_id_str": "380473861", "url": "https://t.co/8htAdoLic9", "id_str": "665388449944440832", "sizes": {"large": {"h": 419, "w": 417, "resize": "fit"}, "small": {"h": 341, "w": 340, "resize": "fit"}, "medium": {"h": 419, "w": 417, "resize": "fit"}, "thumb": {"h": 150, "w": 150, "resize": "crop"}}, "indices": [111, 134], "type": "photo", "id": {"numberLong": "665388449944440832"}, "media_url": "http://pbs.twimg.com/media/CTvvRRSWEAApAlz.jpg"}]}, "_id": {"oid": "5646bbd5bf49a10439b093db"}}]